langextract_outlines/__init__.py
langextract_outlines/_version.py
langextract_outlines/provider.py
langextract_outlines-0.1.3.dist-info/LICENSE
langextract_outlines-0.1.3.dist-info/METADATA
langextract_outlines-0.1.3.dist-info/WHEEL
langextract_outlines-0.1.3.dist-info/entry_points.txt
langextract_outlines-0.1.3.dist-info/top_level.txt
langextract_outlines-0.1.3.dist-info/RECORD
