Metadata-Version: 2.2
Name: langextract-outlines
Version: 0.1.3
Summary: Outlines custom provider plugin for LangExtract
Author: Outlines Developers
License:                                  Apache License
Project-URL: homepage, https://github.com/dottxt-ai/langextract-outlines
Project-URL: repository, https://github.com/dottxt-ai/langextract-outlines
Keywords: machine learning,language models,structured generation
Classifier: Intended Audience :: Developers
Classifier: Intended Audience :: Information Technology
Classifier: Intended Audience :: Science/Research
Classifier: Operating System :: OS Independent
Classifier: Programming Language :: Python :: 3
Classifier: Topic :: Scientific/Engineering :: Artificial Intelligence
Requires-Python: <3.13,>=3.10
License-File: LICENSE
Requires-Dist: langextract>=1.0.0
Requires-Dist: outlines<1.4.0,>=1.0.0
Provides-Extra: test
Requires-Dist: pytest; extra == "test"
Requires-Dist: outlines[transformers]<1.4.0,>=1.0.0; extra == "test"
